investfly/__init__.py
investfly/api/IndicatorApiClient.py
investfly/api/InvestflyApiClient.py
investfly/api/MarketDataApiClient.py
investfly/api/PortfolioApiClient.py
investfly/api/RestApiClient.py
investfly/api/StrategyApiClient.py
investfly/api/__init__.py
investfly/api/py.typed
investfly/cli/InvestflyCli.py
investfly/cli/__init__.py
investfly/models/CommonModels.py
investfly/models/Indicator.py
investfly/models/MarketData.py
investfly/models/MarketDataIds.py
investfly/models/ModelUtils.py
investfly/models/PortfolioModels.py
investfly/models/SecurityFilterModels.py
investfly/models/SecurityUniverseSelector.py
investfly/models/StrategyModels.py
investfly/models/TradingStrategy.py
investfly/models/__init__.py
investfly/models/py.typed
investfly/samples/__init__.py
investfly/samples/indicators/CenterOfGravityOscillator.py
investfly/samples/indicators/ChandelierExit.py
investfly/samples/indicators/DetrendedPriceOscillator.py
investfly/samples/indicators/DonchianChannel.py
investfly/samples/indicators/EhlersAdaptiveRsi.py
investfly/samples/indicators/EhlersFisherTransform.py
investfly/samples/indicators/FisherTransform.py
investfly/samples/indicators/HullMovingAverage.py
investfly/samples/indicators/IndicatorTemplate.py
investfly/samples/indicators/KlingerVolumeOscillator.py
investfly/samples/indicators/NewsSentiment.py
investfly/samples/indicators/RsiOfSma.py
investfly/samples/indicators/SmaEmaAverage.py
investfly/samples/indicators/UltimateOscillator.py
investfly/samples/indicators/__init__.py
investfly/samples/strategies/BollingerBandsMeanReversion.py
investfly/samples/strategies/CryptoArbitrageStrategy.py
investfly/samples/strategies/CryptoMomentumStrategy.py
investfly/samples/strategies/EtfSectorRotationStrategy.py
investfly/samples/strategies/ForexBreakoutStrategy.py
investfly/samples/strategies/ForexCarryTradeStrategy.py
investfly/samples/strategies/IchimokuCloudStrategy.py
investfly/samples/strategies/MacdHistogramStrategy.py
investfly_sdk-1.9.dist-info/LICENSE.txt
investfly_sdk-1.9.dist-info/METADATA
investfly_sdk-1.9.dist-info/WHEEL
investfly_sdk-1.9.dist-info/entry_points.txt
investfly_sdk-1.9.dist-info/top_level.txt
investfly_sdk-1.9.dist-info/RECORD
