Metadata-Version: 2.2
Name: investfly-sdk
Version: 1.9
Summary: Investfly SDK
Author-email: "Investfly.com" <admin@investfly.com>
License: MIT
Project-URL: Homepage, https://www.investfly.com
Classifier: Programming Language :: Python :: 3
Classifier: Operating System :: OS Independent
Requires-Python: >=3.11
License-File: LICENSE.txt
Requires-Dist: mypy>=1.15.0
Requires-Dist: pandas>=2.2.0
Requires-Dist: pandas-stubs>=2.2.0.240218
Requires-Dist: requests>=2.32.3
Requires-Dist: types-requests>=2.32.0.20250602
